{
    "start": "node index.js",
    "name": "weather",
    "actions": [
        {
            "name": "weather.get",
            "description": "Get the weather for a location",
            "parameters": {
                "type": "object",
                "properties": {
                    "locationName": {
                        "type": "string",
                        "description": "The location of the weather",
                        "default": "Users current location"
                    },
                    "date": {
                        "type": "string",
                        "description": "The date of the weather in YYYY-MM-DD format, current date can be retrieved from date.get tool",
                        "default": "The curent date"
                    }
                },
                "required": []
            }
        }
    ]
}